cloudsense/__init__.py
cloudsense/app.py
cloudsense/cli.py
cloudsense/config/__init__.py
cloudsense/config/config.py
cloudsense/static/css/main.css
cloudsense/static/js/main.js
cloudsense/templates/index.html
cloudsense/templates/components/breakdowns.html
cloudsense/templates/components/chart.html
cloudsense/templates/components/header.html
cloudsense/templates/components/metrics.html
cloudsense/templates/components/services.html
cloudsense/utils/__init__.py
cloudsense/utils/cache.py
cloudsense/utils/helpers.py
cloudsense/utils/validators.py
cloudsense-0.3.0.dist-info/licenses/LICENSE
cloudsense-0.3.0.dist-info/METADATA
cloudsense-0.3.0.dist-info/WHEEL
cloudsense-0.3.0.dist-info/entry_points.txt
cloudsense-0.3.0.dist-info/top_level.txt
cloudsense-0.3.0.dist-info/RECORD
