Metadata-Version: 2.4
Name: cloudsense
Version: 0.3.0
Summary: A CLI and interactive GUI for AWS cost tracking.
Author: Veloduff
License: MIT
Project-URL: Homepage, https://github.com/veloduff/cloudsense
Project-URL: Repository, https://github.com/veloduff/cloudsense
Project-URL: Issues, https://github.com/veloduff/cloudsense/issues
Keywords: aws,cost,budget,cli,dashboard,monitoring,cloud,gui
Classifier: Development Status :: 4 - Beta
Classifier: Intended Audience :: Developers
Classifier: License :: OSI Approved :: MIT License
Classifier: Programming Language :: Python :: 3
Classifier: Programming Language :: Python :: 3.8
Classifier: Programming Language :: Python :: 3.9
Classifier: Programming Language :: Python :: 3.10
Classifier: Programming Language :: Python :: 3.11
Classifier: Topic :: System :: Monitoring
Classifier: Topic :: Internet :: WWW/HTTP :: WSGI :: Application
Requires-Python: >=3.8
License-File: LICENSE
Requires-Dist: flask>=3.0.0
Requires-Dist: boto3>=1.26.0
Requires-Dist: flask-limiter>=3.3.0
Requires-Dist: Werkzeug>=3.0.0
Dynamic: license-file
